{"Source": "Evergreen", "SCAC": "EGLV", "Vessel Name": "EVER LEADER", "Voyage Number": "0911-041E", "Vessel Stops": {"QINGDAO": {"Estimated Arrival": "07/23", "Estimated Departure": "07/25"}, "NINGBO": {"Estimated Arrival": "07/26", "Estimated Departure": "07/27"}, "SHANGHAI": {"Estimated Arrival": "07/28", "Estimated Departure": "07/29"}, "PUSAN": {"Estimated Arrival": "07/30", "Estimated Departure": "07/31"}, "PANAMA CANAL": {"Estimated Arrival": "08/17", "Estimated Departure": "08/18"}, "COLON CONTAINER TERMINAL": {"Estimated Arrival": "08/18", "Estimated Departure": "08/19"}, "SAVANNAH": {"Estimated Arrival": "08/23", "Estimated Departure": "08/24"}, "CHARLESTON": {"Estimated Arrival": "08/25", "Estimated Departure": "08/26"}, "BOSTON": {"Estimated Arrival": "08/28", "Estimated Departure": "08/29"}, "NEW YORK": {"Estimated Arrival": "08/30", "Estimated Departure": "08/31"}}}